agent_context_protocol/__init__.py
agent_context_protocol/acp_manager.py
agent_context_protocol/agent.py
agent_context_protocol/base.py
agent_context_protocol/dag_compiler.py
agent_context_protocol/mcp_node.py
agent_context_protocol/task_decomposer.py
agent_context_protocol/available_tools/__init__.py
agent_context_protocol/available_tools/function_format/__init__.py
agent_context_protocol/available_tools/function_format/perplexity_function.py
agent_context_protocol/available_tools/function_format/return_dict.py
agent_context_protocol/available_tools/function_format/text2image_function.py
agent_context_protocol/available_tools/hardcoded_format/__init__.py
agent_context_protocol/available_tools/hardcoded_format/news_api_everything.py
agent_context_protocol/available_tools/hardcoded_format/news_api_top_headlines.py
agent_context_protocol/available_tools/hardcoded_format/perplexity.py
agent_context_protocol/available_tools/hardcoded_format/return_dict.py
agent_context_protocol/available_tools/openapi_format/__init__.py
agent_context_protocol/available_tools/openapi_format/return_dict.py
agent_context_protocol/available_tools/rapid_apis_format/__init__.py
agent_context_protocol/available_tools/rapid_apis_format/return_dict.py
agent_context_protocol/external_env_details/__init__.py
agent_context_protocol/external_env_details/brief_details.json
agent_context_protocol/external_env_details/executable-spec-converted.json
agent_context_protocol/external_env_details/stackexchange.yaml
agent_context_protocol/external_env_details/tool_keys.json
agent_context_protocol/external_env_details/weather_api.yml
agent_context_protocol/prompts/__init__.py
agent_context_protocol/prompts/dashboard_prompt.txt
agent_context_protocol/prompts/task_decomposer_system_prompt.txt
agent_context_protocol/prompts/agent/__init__.py
agent_context_protocol/prompts/agent/agent_request_prompt.txt
agent_context_protocol/prompts/agent/agent_response_prompt.txt
agent_context_protocol-0.3.1.dist-info/LICENSE
agent_context_protocol-0.3.1.dist-info/METADATA
agent_context_protocol-0.3.1.dist-info/WHEEL
agent_context_protocol-0.3.1.dist-info/top_level.txt
agent_context_protocol-0.3.1.dist-info/RECORD
