Metadata-Version: 2.1
Name: agent-context-protocol
Version: 0.3.1
Summary: A multi agent communication toolkit.
Classifier: Programming Language :: Python :: 3
Classifier: License :: OSI Approved :: MIT License
Requires-Python: >=3.7
License-File: LICENSE
Requires-Dist: streamlit
Requires-Dist: openai
Requires-Dist: tiktoken
Requires-Dist: pyvis
Requires-Dist: mcp
Requires-Dist: matplotlib
Requires-Dist: pyyaml
